imagemv/__init__.py
imagemv/cli.py
imagemv/datefunctions.py
imagemv/fileinfo.py
imagemv/metadata.py
imagemv/processstats.py
imagemv-0.4.0.dist-info/LICENSE
imagemv-0.4.0.dist-info/METADATA
imagemv-0.4.0.dist-info/WHEEL
imagemv-0.4.0.dist-info/entry_points.txt
imagemv-0.4.0.dist-info/top_level.txt
imagemv-0.4.0.dist-info/RECORD
