Metadata-Version: 2.1
Name: imagemv
Version: 0.4.0
Summary: Move photos and videos into a directory tree structure sorted by date taken
Author-email: ttime <tmp-imagemv@danieljames.ch>
Project-URL: Homepage, https://gitlab.com/ttime/imagemv
Project-URL: Bug Tracker, https://gitlab.com/ttime/imagemv/-/issues
Classifier: Environment :: Console
Classifier: Intended Audience :: System Administrators
Classifier: License :: OSI Approved :: GNU General Public License v3 or later (GPLv3+)
Classifier: Operating System :: OS Independent
Classifier: Programming Language :: Python :: 3
Classifier: Topic :: Multimedia :: Graphics
Classifier: Topic :: Multimedia :: Video
Classifier: Topic :: System :: Archiving
Requires-Python: >=3.9
License-File: LICENSE
